setup.py
keras_dense_sparse_matmul/__init__.py
keras_dense_sparse_matmul.egg-info/PKG-INFO
keras_dense_sparse_matmul.egg-info/SOURCES.txt
keras_dense_sparse_matmul.egg-info/dependency_links.txt
keras_dense_sparse_matmul.egg-info/not-zip-safe
keras_dense_sparse_matmul.egg-info/requires.txt
keras_dense_sparse_matmul.egg-info/top_level.txt